itk/TwoProjectionRegistrationPython.py
itk/_TwoProjectionRegistrationPython.pyd
itk/__init_twoprojectionregistration__.py
itk/itkNormalizedCorrelationTwoImageToOneImageMetricPython.py
itk/itkSiddonJacobsRayCastInterpolateImageFunctionPython.py
itk/itkTwoImageToOneImageMetricPython.py
itk/itkTwoProjectionImageRegistrationMethodPython.py
itk/Configuration/TwoProjectionRegistrationConfig.py
itk/Configuration/TwoProjectionRegistration_snake_case.py
itk_twoprojectionregistration-2.0.1.dist-info/licenses/LICENSE
itk_twoprojectionregistration.libs/msvcp140.dll
itk_twoprojectionregistration.libs/tbb12.dll
itk_twoprojectionregistration-2.0.1.dist-info/DELVEWHEEL
itk_twoprojectionregistration-2.0.1.dist-info/METADATA
itk_twoprojectionregistration-2.0.1.dist-info/WHEEL
itk_twoprojectionregistration-2.0.1.dist-info/RECORD
